dspy_inspector/__init__.py
dspy_inspector/inspector.py
dspy_inspector/inspector_test.py
dspy_inspector/styles.css
dspy_inspector/styles.css.map
dspy_inspector/styles.scss
dspy_inspector-0.7.0.dist-info/LICENSE
dspy_inspector-0.7.0.dist-info/METADATA
dspy_inspector-0.7.0.dist-info/WHEEL
dspy_inspector-0.7.0.dist-info/RECORD
