Metadata-Version: 2.1
Name: dspy-inspector
Version: 0.7.0
Summary: DSPy program/pipeline inspector widget for Jupyter/VSCode Notebooks.
Home-page: https://github.com/neoxelox/dspy-inspector
License: GPL-3.0
Keywords: dspy,inspector,program,pipeline,plugin,widget,notebook,jupyter,vscode,dspy-inspector
Author: Alex Rodriguez
Author-email: me@arn.sh
Maintainer: Alex Rodriguez
Maintainer-email: me@arn.sh
Requires-Python: >=3.11,<4.0
Classifier: License :: OSI Approved :: GNU General Public License v3 (GPLv3)
Classifier: Programming Language :: Python :: 3
Classifier: Programming Language :: Python :: 3.11
Classifier: Programming Language :: Python :: 3.12
Requires-Dist: dspy-ai (==2.1.10)
Requires-Dist: ipycytoscape (==1.3.3)
Requires-Dist: ipywidgets (>=8.1.1,<9.0.0)
Requires-Dist: jupyterlab-widgets (>=3.0.9,<4.0.0)
Requires-Dist: orjson (>=3.9.13,<4.0.0)
Requires-Dist: tiktoken (>=0.5.2,<0.6.0)
Project-URL: Documentation, https://github.com/neoxelox/dspy-inspector
Project-URL: Repository, https://github.com/neoxelox/dspy-inspector
